dool/__init__.py
dool/__main__.py
dool/plugins/dool_apache.py
dool/plugins/dool_battery.py
dool/plugins/dool_battery_remain.py
dool/plugins/dool_bond.py
dool/plugins/dool_condor_queue.py
dool/plugins/dool_cpufreq.py
dool/plugins/dool_dbus.py
dool/plugins/dool_disk_avgqu.py
dool/plugins/dool_disk_avgrq.py
dool/plugins/dool_disk_inflight.py
dool/plugins/dool_disk_svctm.py
dool/plugins/dool_disk_tps.py
dool/plugins/dool_disk_util.py
dool/plugins/dool_disk_wait.py
dool/plugins/dool_dool.py
dool/plugins/dool_dool_cpu.py
dool/plugins/dool_dool_ctxt.py
dool/plugins/dool_dool_mem.py
dool/plugins/dool_dool_step.py
dool/plugins/dool_fan.py
dool/plugins/dool_freespace.py
dool/plugins/dool_fuse.py
dool/plugins/dool_gpfs.py
dool/plugins/dool_gpfs_ops.py
dool/plugins/dool_helloworld.py
dool/plugins/dool_ib.py
dool/plugins/dool_innodb_buffer.py
dool/plugins/dool_innodb_io.py
dool/plugins/dool_innodb_ops.py
dool/plugins/dool_jvm_full.py
dool/plugins/dool_jvm_vm.py
dool/plugins/dool_lnet.py
dool/plugins/dool_lustre.py
dool/plugins/dool_md_status.py
dool/plugins/dool_mem_percent.py
dool/plugins/dool_memcache_hits.py
dool/plugins/dool_mongodb_conn.py
dool/plugins/dool_mongodb_mem.py
dool/plugins/dool_mongodb_opcount.py
dool/plugins/dool_mongodb_queue.py
dool/plugins/dool_mongodb_stats.py
dool/plugins/dool_mysql_cmds.py
dool/plugins/dool_mysql_conn.py
dool/plugins/dool_mysql_innodb.py
dool/plugins/dool_mysql_io.py
dool/plugins/dool_mysql_keys.py
dool/plugins/dool_net_packets.py
dool/plugins/dool_nfs3.py
dool/plugins/dool_nfs3_ops.py
dool/plugins/dool_nfsd3.py
dool/plugins/dool_nfsd3_ops.py
dool/plugins/dool_nfsd4_ops.py
dool/plugins/dool_nfsstat4.py
dool/plugins/dool_ntp.py
dool/plugins/dool_pid_detail.py
dool/plugins/dool_postfix.py
dool/plugins/dool_power.py
dool/plugins/dool_proc_count.py
dool/plugins/dool_qmail.py
dool/plugins/dool_redis.py
dool/plugins/dool_rpc.py
dool/plugins/dool_rpcd.py
dool/plugins/dool_sendmail.py
dool/plugins/dool_skel.py
dool/plugins/dool_snmp_cpu.py
dool-1.3.8.dist-info/entry_points.txt
dool-1.3.8.dist-info/licenses/LICENSE
dool-1.3.8.dist-info/WHEEL
dool-1.3.8.dist-info/METADATA
dool-1.3.8.dist-info/RECORD
