Metadata-Version: 2.4
Name: dool
Version: 1.3.8
Summary: Dool is a command line tool to monitor many aspects of your system: CPU,
Author-email: Scott Baker <scott@perturb.org>
Requires-Python: ~=3.5
Classifier: License :: OSI Approved :: GNU General Public License v3 or later (GPLv3+)
License-File: LICENSE
Project-URL: Home, https://github.com/scottchiefbaker/dool
